{
"path": "/home/robbis/git/pyitab/pyitab/io/data/fmri",
"experiment": "episodic_memory",
"task": "fmri",
"analysis": "searchlight",
"estimator": "Pipeline(memory=None,\n     steps=[('clf', SVC(C=1, cache_size=200, class_weight=None, coef0=0.0,\n  decision_function_shape='ovr', degree=3, gamma='auto_deprecated',\n  kernel='linear', max_iter=-1, probability=False, random_state=None,\n  shrinking=True, tol=0.001, verbose=False))])",
"scoring": "{'accuracy': make_scorer(accuracy_score), 'roc_auc': make_scorer(roc_auc_score, needs_threshold=True)}",
"cv": "LeaveOneGroupOut()",
"permutation": "0",
"targets": "['F' 'L']",
"chunks": "[0]",
"time_indices": "[ 0  1  2  3  4  5  6  7  8  9 10 11 12 13 14 15 16 17 18 19 20 21 22 23\n 24 25 26 27 28 29]",
"time_coords": "[ 0.  1.  2.  3.  4.  5.  6.  7.  8.  9. 10. 11. 12. 13. 14. 15. 16. 17.\n 18. 19. 20. 21. 22. 23. 24. 25. 26. 27. 28. 29.]",
"file": "[1]",
"events_number": "[ 1  2  3  4  5  6  7  8  9 10 11 12 13 14 15 16 17 18 19 20 21 22 23 24\n 25 26 27 28 29]",
"name": "['subj01' 'subj02' 'subj03' 'subj04']",
"stim": "['F' 'L' 'N']",
"evidence": "[0 1 2 3]",
"accuracy": "['0' 'C' 'I']",
"memory_status": "['F' 'L']",
"decision": "['F' 'L' 'N']",
"trial_decoding": "['F' 'L']",
"trial": "[0 1 2]",
"subject": "['subj01' 'subj02' 'subj03' 'subj04']",
"group": "['1']",
"group_split": "['1']",
"age": "['22' '25' '27' '32']",
"summary": "Dataset: 120x843@float64, <sa: accuracy,age,chunks,decision,events_number,evidence,file,group,group_split,memory_status,name,stim,subject,targets,time_coords,time_indices,trial,trial_decoding>, <...\nstats: mean=8.42874e-19 std=1 var=1 min=-3.92003 max=4.19432\n\nCounts of targets in each chunk:\n  chunks\\targets  F   L\n                 --- ---\n        0         60  60\n\nSummary for targets across chunks\n  targets mean std min max #chunks\n    F      60   0   60  60    1\n    L      60   0   60  60    1\n\nSummary for chunks across targets\n  chunks mean std min max #targets\n    0     60   0   60  60     2\nSequence statistics for 120 entries from set ['F', 'L']\nCounter-balance table for orders up to 2:\nTargets/Order O1     |  O2     |\n      F:      30 30  |  27 33  |\n      L:      30 29  |  32 26  |\nCorrelations: min=-0.37 max=0.23 mean=-0.0084 sum(abs)=9.3",
"radius": "9.0"
}